LICENSE.md
MANIFEST.in
README.md
setup.py
tests/__init__.py
tests/test_tkbl.py
tkbl/__init__.py
tkbl/tkbl.py
tkbl.egg-info/PKG-INFO
tkbl.egg-info/SOURCES.txt
tkbl.egg-info/dependency_links.txt
tkbl.egg-info/requires.txt
tkbl.egg-info/top_level.txt
tkbl/data/ESTCP_uniformat.csv
tkbl/data/SFTool_uniformat.csv
tkbl/data/Table_A1_Federal_BPS.csv
tkbl/data/Table_A2_Federal_BPS.csv
tkbl/data/building-sync-eem.csv
tkbl/data/building-sync-ground-truth.csv
tkbl/data/building-sync-ground-truth_JX.csv
tkbl/data/federal-bps.csv