Metadata-Version: 2.1
Name: tkbl
Version: 0.7
Summary: A package for finding results from SFTool and ESTCP projects based off of uniformat codes
Home-page: UNKNOWN
Author: Brian L Ball
License: BSD5
Platform: UNKNOWN
License-File: LICENSE.md
